{"header":{"PPQ":128,"bpm":120,"name":""},"startTime":0,"duration":9.25,"tracks":[{"startTime":0,"duration":9.25,"length":15,"notes":[{"name":"C5","midi":72,"time":0,"velocity":0.7086614173228346,"duration":1},{"name":"A4","midi":69,"time":1,"velocity":0.7086614173228346,"duration":1},{"name":"E4","midi":64,"time":2,"velocity":0.7086614173228346,"duration":0.25},{"name":"F4","midi":65,"time":2.25,"velocity":0.7086614173228346,"duration":0.25},{"name":"A4","midi":69,"time":2.5,"velocity":0.7086614173228346,"duration":1},{"name":"G4","midi":67,"time":3.5,"velocity":0.7086614173228346,"duration":0.5},{"name":"E4","midi":64,"time":4,"velocity":0.7086614173228346,"duration":1},{"name":"A4","midi":69,"time":5,"velocity":0.7086614173228346,"duration":1},{"name":"G4","midi":67,"time":6,"velocity":0.7086614173228346,"duration":0.125},{"name":"E4","midi":64,"time":6.125,"velocity":0.7086614173228346,"duration":0.25},{"name":"A4","midi":69,"time":6.375,"velocity":0.7086614173228346,"duration":1},{"name":"F4","midi":65,"time":7.375,"velocity":0.7086614173228346,"duration":0.25},{"name":"B4","midi":71,"time":7.625,"velocity":0.7086614173228346,"duration":0.5},{"name":"A4","midi":69,"time":8.125,"velocity":0.7086614173228346,"duration":0.125},{"name":"A4","midi":69,"time":8.25,"velocity":0.7086614173228346,"duration":1}],"controlChanges":{},"id":0,"channelNumber":0,"isPercussion":false}]}