{"header":{"PPQ":128,"bpm":120,"name":""},"startTime":0,"duration":6.75,"tracks":[{"startTime":0,"duration":6.75,"length":11,"notes":[{"name":"E4","midi":64,"time":0,"velocity":0.7086614173228346,"duration":0.5},{"name":"B3","midi":59,"time":0.5,"velocity":0.7086614173228346,"duration":0.5},{"name":"C4","midi":60,"time":1,"velocity":0.7086614173228346,"duration":0.25},{"name":"G3","midi":55,"time":1.25,"velocity":0.7086614173228346,"duration":0.25},{"name":"B3","midi":59,"time":1.5,"velocity":0.7086614173228346,"duration":0.5},{"name":"D4","midi":62,"time":2,"velocity":0.7086614173228346,"duration":1},{"name":"A3","midi":57,"time":3,"velocity":0.7086614173228346,"duration":1},{"name":"F3","midi":53,"time":4,"velocity":0.7086614173228346,"duration":0.5},{"name":"B3","midi":59,"time":4.5,"velocity":0.7086614173228346,"duration":1},{"name":"A3","midi":57,"time":5.5,"velocity":0.7086614173228346,"duration":1},{"name":"D4","midi":62,"time":6.5,"velocity":0.7086614173228346,"duration":0.25}],"controlChanges":{},"id":0,"channelNumber":0,"isPercussion":false}]}