{"header":{"PPQ":128,"bpm":120,"name":""},"startTime":0,"duration":1,"tracks":[{"startTime":0,"duration":1,"length":11,"notes":[{"name":"F3","midi":53,"time":0,"velocity":0.7086614173228346,"duration":0.5},{"name":"G3","midi":55,"time":0,"velocity":0.7086614173228346,"duration":0.5},{"name":"A#3","midi":58,"time":0,"velocity":0.7086614173228346,"duration":0.5},{"name":"F4","midi":65,"time":0,"velocity":0.7086614173228346,"duration":0.5},{"name":"A#4","midi":70,"time":0,"velocity":0.7086614173228346,"duration":0.5},{"name":"G5","midi":79,"time":0,"velocity":0.7086614173228346,"duration":0.5},{"name":"C#3","midi":49,"time":0.5,"velocity":0.7086614173228346,"duration":0.5},{"name":"A3","midi":57,"time":0.5,"velocity":0.7086614173228346,"duration":0.5},{"name":"F#4","midi":66,"time":0.5,"velocity":0.7086614173228346,"duration":0.5},{"name":"A#4","midi":70,"time":0.5,"velocity":0.7086614173228346,"duration":0.5},{"name":"F5","midi":77,"time":0.5,"velocity":0.7086614173228346,"duration":0.5}],"controlChanges":{},"id":0,"channelNumber":0,"isPercussion":false}]}